README.md
setup.py
SIPSimR/__init__.py
SIPSimR.egg-info/PKG-INFO
SIPSimR.egg-info/SOURCES.txt
SIPSimR.egg-info/dependency_links.txt
SIPSimR.egg-info/top_level.txt
scripts/BD_span_calc.R
scripts/DESeq2_addInfo.R
scripts/DESeq2_combine.R
scripts/DESeq2_confuseMtx.R
scripts/DESeq2_listTaxa.R
scripts/DESeq2_rare-dominant.R
scripts/OTU_taxonAbund.R
scripts/comm_add_richness.R
scripts/comm_add_target.R
scripts/comm_beta_div.R
scripts/comm_set_abund.R
scripts/comm_shuffle_taxa.R
scripts/correlogram_make.R
scripts/heavy_confuseMtx.R
scripts/phyloseq2comm.R
scripts/phyloseq_DESeq2.R
scripts/phyloseq_edit.R
scripts/phyloseq_make.R
scripts/phyloseq_ordination.R
scripts/qSIP_confuseMtx.R
scripts/rTraitContW.R
scripts/shannon_calc.R