Metadata-Version: 1.0
Name: SIPSimR
Version: 0.1
Summary: Simulate High Resolution Stable Isotope Probing Datasets (associated R scripts)
Home-page: https://github.com/nick-youngblut/SIPSimR
Author: Nick Youngblut
Author-email: nyoungb2@gmail.com
License: MIT license
Platform: UNKNOWN
